ebpkg/metadata.py
ebpkg/cli/__init__.py
ebpkg-0.0.1.dist-info/METADATA
ebpkg-0.0.1.dist-info/WHEEL
ebpkg-0.0.1.dist-info/entry_points.txt
ebpkg-0.0.1.dist-info/RECORD
