Metadata-Version: 2.4
Name: ebpkg
Version: 0.0.1
Project-URL: Documentation, https://ebpkg.github.io
Project-URL: Issues, https://github.com/ebpkg/ebpkg/issues
Project-URL: Source, https://github.com/ebpkg/ebpkg
Author-email: Jayesh Badwaik <j.badwaik@fz-juelich.de>
License-Expression: GPL-2.0-only
Requires-Dist: semver
